IPAkor/__init__.py
IPAkor/border_maker.py
IPAkor/transcription.py
IPAkor/static/final_trans.csv
IPAkor-2.6.0.dist-info/METADATA
IPAkor-2.6.0.dist-info/WHEEL
IPAkor-2.6.0.dist-info/top_level.txt
IPAkor-2.6.0.dist-info/RECORD
