Metadata-Version: 2.1
Name: IPAkor
Version: 2.6.0
Author-email: neminova2.0@gmail.com
Classifier: Programming Language :: Python :: 3
Classifier: Operating System :: OS Independent
Classifier: Topic :: Scientific/Engineering
Requires-Python: >=3
Requires-Dist: konlpy
Requires-Dist: wget
